paramus/__init__.py
paramus/world/__init__.py
paramus/world/client/__init__.py
paramus/world/client/client.py
paramus_world-1.0.2.dist-info/METADATA
paramus_world-1.0.2.dist-info/WHEEL
paramus_world-1.0.2.dist-info/top_level.txt
paramus_world-1.0.2.dist-info/RECORD
