Metadata-Version: 2.4
Name: paramus-world
Version: 1.0.2
Summary: Paramus World Client - API client for the Paramus World semantic knowledge graph system
Home-page: https://paramus.ai/paramus-world/
Author: Thorsten Gressling
Author-email: Thorsten Gressling <gressling@paramus.ai>
License: Proprietary
Project-URL: Homepage, https://paramus.ai/paramus-world/
Project-URL: Repository, https://github.com/gressling/paramus-world-client
Project-URL: Issues, https://github.com/gressling/paramus-world-client/issues
Project-URL: Documentation, https://paramus-world-client.readthedocs.io/en/latest/
Keywords: semantic API,knowledge graph,SPARQL,JSON-RPC,paramus,world,client,api
Classifier: Development Status :: 5 - Production/Stable
Classifier: Intended Audience :: Developers
Classifier: Intended Audience :: Science/Research
Classifier: Operating System :: OS Independent
Classifier: Programming Language :: Python :: 3
Classifier: Programming Language :: Python :: 3.8
Classifier: Programming Language :: Python :: 3.9
Classifier: Programming Language :: Python :: 3.10
Classifier: Programming Language :: Python :: 3.11
Classifier: Programming Language :: Python :: 3.12
Classifier: Programming Language :: Python :: 3.13
Classifier: Topic :: Software Development :: Libraries :: Python Modules
Classifier: Topic :: Internet :: WWW/HTTP :: HTTP Servers
Classifier: Topic :: Scientific/Engineering :: Artificial Intelligence
Requires-Python: >=3.8
Requires-Dist: requests>=2.25.0
Requires-Dist: numpy>=1.20.0
Requires-Dist: scipy>=1.7.0
Requires-Dist: matplotlib>=3.3.0
Provides-Extra: dev
Requires-Dist: pytest>=6.0; extra == "dev"
Requires-Dist: black; extra == "dev"
Requires-Dist: flake8; extra == "dev"
Requires-Dist: mypy; extra == "dev"
Provides-Extra: optimization
Requires-Dist: cvxpy>=1.1.0; extra == "optimization"
Requires-Dist: gekko>=1.0.0; extra == "optimization"
Dynamic: author
Dynamic: home-page
Dynamic: requires-python
